tiling/__init__.py
tiling/const_size.py
tiling/const_stride.py
tiling-0.3.0.dist-info/LICENSE.md
tiling-0.3.0.dist-info/METADATA
tiling-0.3.0.dist-info/WHEEL
tiling-0.3.0.dist-info/top_level.txt
tiling-0.3.0.dist-info/RECORD
