Metadata-Version: 2.1
Name: tiling
Version: 0.3.0
Summary: Minimalistic set of image reader agnostic tools to easily iterate over large images
Home-page: https://github.com/vfdev-5/ImageTilingUtils
Author: vfdev-5
Author-email: vfdev.5@gmail.com
License: MIT
Platform: UNKNOWN
Requires-Dist: six
Provides-Extra: tests
Requires-Dist: pytest ; extra == 'tests'
Requires-Dist: pytest-cov ; extra == 'tests'
